DRL/__init__.py
DRL/ddpg.py
DRL/dqn.py
DRL/pg.py
DRL/ppo.py
DRL/sac.py
DRL/td3.py
tests/__init__.py
tests/test_DDPG.py
tests/test_DQN.py
tests/test_PG.py
tests/test_PPO.py
tests/test_SAC.py
tests/test_TD3.py
Python_DRL-1.0.1.dist-info/LICENSE
Python_DRL-1.0.1.dist-info/METADATA
Python_DRL-1.0.1.dist-info/WHEEL
Python_DRL-1.0.1.dist-info/top_level.txt
Python_DRL-1.0.1.dist-info/RECORD
