Metadata-Version: 2.1
Name: Python-DRL
Version: 1.0.1
Summary: A pytorch-based deep reinforcement learning package
Home-page: https://github.com/lyuanzhi/Python-DRL
Author: lyuanzhi
Author-email: lyuanzhi862066195@outlook.com
Classifier: Development Status :: 3 - Alpha
Classifier: Intended Audience :: Developers
Classifier: License :: OSI Approved :: MIT License
Classifier: Programming Language :: Python :: 3
Classifier: Programming Language :: Python :: 3.8
Classifier: Programming Language :: Python :: 3.9
Classifier: Programming Language :: Python :: 3.10
License-File: LICENSE
Requires-Dist: numpy ~=1.23.0
Requires-Dist: torch >=2.0.1
Requires-Dist: gym ~=0.26.2
Requires-Dist: opencv-python >=4.5.5.62
Requires-Dist: pygame ~=2.5.2
